[{"id":"9205020001","district_id":"9205020","name":"BONEM"},{"id":"9205020002","district_id":"9205020","name":"MEGA"},{"id":"9205020003","district_id":"9205020","name":"KWADE"},{"id":"9205020004","district_id":"9205020","name":"WARAFOR"},{"id":"9205020005","district_id":"9205020","name":"MALAWORSAI"},{"id":"9205020006","district_id":"9205020","name":"WARMASI"},{"id":"9205020007","district_id":"9205020","name":"NAMUAS"},{"id":"9205020008","district_id":"9205020","name":"SALEWOK"},{"id":"9205020009","district_id":"9205020","name":"WARMANEN"}]