[{"id":"9501160001","district_id":"9501160","name":"KAMANGI"},{"id":"9501160002","district_id":"9501160","name":"YASA MULYA"},{"id":"9501160003","district_id":"9501160","name":"SUMBER HARAPAN"},{"id":"9501160004","district_id":"9501160","name":"ISANOMBIAS"},{"id":"9501160005","district_id":"9501160","name":"WANINGGAP MIRAF"},{"id":"9501160006","district_id":"9501160","name":"WANINGGAP SAY"},{"id":"9501160007","district_id":"9501160","name":"AMUNKAI"},{"id":"9501160008","district_id":"9501160","name":"HIDUP BARU"},{"id":"9501160009","district_id":"9501160","name":"YABA MARU"},{"id":"9501160010","district_id":"9501160","name":"TAMBAT"},{"id":"9501160011","district_id":"9501160","name":"SERMAYAM INDAH"},{"id":"9501160012","district_id":"9501160","name":"NGGUTI BOB"},{"id":"9501160013","district_id":"9501160","name":"SOA"},{"id":"9501160014","district_id":"9501160","name":"BERSEHATI"}]