[{"id":"9608190001","district_id":"9608190","name":"TORAGE"},{"id":"9608190002","district_id":"9608190","name":"PALUMAGI"},{"id":"9608190003","district_id":"9608190","name":"JIRAMOK"},{"id":"9608190004","district_id":"9608190","name":"YANENGGAWI"},{"id":"9608190005","district_id":"9608190","name":"WURABUME"},{"id":"9608190006","district_id":"9608190","name":"BINGGELUME"},{"id":"9608190007","district_id":"9608190","name":"KAYOGEBUR"},{"id":"9608190008","district_id":"9608190","name":"KALOME"},{"id":"9608190009","district_id":"9608190","name":"AGAPE"},{"id":"9608190010","district_id":"9608190","name":"CILOME"},{"id":"9608190011","district_id":"9608190","name":"LONGGAWI"},{"id":"9608190012","district_id":"9608190","name":"WUNDINI"},{"id":"9608190013","district_id":"9608190","name":"BEREM"},{"id":"9608190014","district_id":"9608190","name":"DIRALUK"},{"id":"9608190015","district_id":"9608190","name":"PILIBUR"},{"id":"9608190016","district_id":"9608190","name":"JINGGWI"}]