[{"id":"9704100001","district_id":"9704100","name":"ENANAGI"},{"id":"9704100002","district_id":"9704100","name":"AROMBOK"},{"id":"9704100003","district_id":"9704100","name":"WURINERI"},{"id":"9704100004","district_id":"9704100","name":"KERIBAGA"},{"id":"9704100005","district_id":"9704100","name":"PINDAK"},{"id":"9704100006","district_id":"9704100","name":"GILOPAGA"},{"id":"9704100007","district_id":"9704100","name":"POKEGI"},{"id":"9704100008","district_id":"9704100","name":"WONA"},{"id":"9704100009","district_id":"9704100","name":"NUMBOBOTON"}]