[{"id":"9503110001","district_id":"9503110","name":"SIGARE"},{"id":"9503110002","district_id":"9503110","name":"KAITOK"},{"id":"9503110003","district_id":"9503110","name":"HOMANG"},{"id":"9503110004","district_id":"9503110","name":"JUFO KECIL"},{"id":"9503110005","district_id":"9503110","name":"ECI"},{"id":"9503110006","district_id":"9503110","name":"YAME"},{"id":"9503110007","district_id":"9503110","name":"ABOGE"},{"id":"9503110008","district_id":"9503110","name":"KOPI"},{"id":"9503110009","district_id":"9503110","name":"ISAGE"},{"id":"9503110010","district_id":"9503110","name":"KIKI"},{"id":"9503110011","district_id":"9503110","name":"KHABU"},{"id":"9503110012","district_id":"9503110","name":"JUFO BESAR"},{"id":"9503110013","district_id":"9503110","name":"KERU"},{"id":"9503110014","district_id":"9503110","name":"ASAREN"},{"id":"9503110015","district_id":"9503110","name":"CHANANI"},{"id":"9503110016","district_id":"9503110","name":"GIRIMIO"},{"id":"9503110017","district_id":"9503110","name":"HAFFO"},{"id":"9503110018","district_id":"9503110","name":"MEDA"}]