[{"id":"9704180001","district_id":"9704180","name":"WANGGULAM"},{"id":"9704180002","district_id":"9704180","name":"NOGOBUMBU"},{"id":"9704180003","district_id":"9704180","name":"GABUNGGOBAK"},{"id":"9704180004","district_id":"9704180","name":"BILUBAGA"},{"id":"9704180005","district_id":"9704180","name":"BITILABUR"},{"id":"9704180006","district_id":"9704180","name":"ABENA"},{"id":"9704180007","district_id":"9704180","name":"WULURIK"},{"id":"9704180008","district_id":"9704180","name":"ARELAM"},{"id":"9704180009","district_id":"9704180","name":"GELALO"},{"id":"9704180010","district_id":"9704180","name":"YIBALO"},{"id":"9704180011","district_id":"9704180","name":"WINDIK"},{"id":"9704180012","district_id":"9704180","name":"YINAMA"},{"id":"9704180013","district_id":"9704180","name":"DUMA"},{"id":"9704180014","district_id":"9704180","name":"WANIA"}]