[{"id":"9704200001","district_id":"9704200","name":"FINAI"},{"id":"9704200002","district_id":"9704200","name":"GUALO"},{"id":"9704200003","district_id":"9704200","name":"DIMBUGUL"},{"id":"9704200004","district_id":"9704200","name":"HOLANDIA"},{"id":"9704200005","district_id":"9704200","name":"YOGWEME"},{"id":"9704200006","district_id":"9704200","name":"TAWI"},{"id":"9704200007","district_id":"9704200","name":"WINA"},{"id":"9704200008","district_id":"9704200","name":"YUGUMENGGA"},{"id":"9704200009","district_id":"9704200","name":"WARIRU"},{"id":"9704200010","district_id":"9704200","name":"YUGUBUK"},{"id":"9704200011","district_id":"9704200","name":"AKIMA"},{"id":"9704200012","district_id":"9704200","name":"MALELA"},{"id":"9704200013","district_id":"9704200","name":"NAKWIL"}]