[{"id":"9708320001","district_id":"9708320","name":"BATOM"},{"id":"9708320002","district_id":"9708320","name":"OKSIP"},{"id":"9708320003","district_id":"9708320","name":"SABI"},{"id":"9708320004","district_id":"9708320","name":"BATOM DUA"},{"id":"9708320005","district_id":"9708320","name":"NEEP"},{"id":"9708320006","district_id":"9708320","name":"MUARA"},{"id":"9708320007","district_id":"9708320","name":"OKYAKO"},{"id":"9708320008","district_id":"9708320","name":"MONGHAM"},{"id":"9708320009","district_id":"9708320","name":"BELOMO"},{"id":"9708320010","district_id":"9708320","name":"PETENG"},{"id":"9708320011","district_id":"9708320","name":"ABUKEROM"}]